nengo_sphinx_theme/__init__.py
nengo_sphinx_theme/version.py
nengo_sphinx_theme/ext/__init__.py
nengo_sphinx_theme/ext/autoautosummary.py
nengo_sphinx_theme/ext/backoff.py
nengo_sphinx_theme/ext/redirects.py
nengo_sphinx_theme/ext/resolvedefaults.py
nengo_sphinx_theme/ext/sourcelinks.py
nengo_sphinx_theme/theme/404.html
nengo_sphinx_theme/theme/footer.html
nengo_sphinx_theme/theme/layout.html
nengo_sphinx_theme/theme/navbar.html
nengo_sphinx_theme/theme/searchbox.html
nengo_sphinx_theme/theme/sidebar.html
nengo_sphinx_theme/theme/sourcelink.html
nengo_sphinx_theme/theme/theme.conf
nengo_sphinx_theme-20.9.dist-info/LICENSE.rst
nengo_sphinx_theme-20.9.dist-info/METADATA
nengo_sphinx_theme-20.9.dist-info/WHEEL
nengo_sphinx_theme-20.9.dist-info/entry_points.txt
nengo_sphinx_theme-20.9.dist-info/top_level.txt
nengo_sphinx_theme-20.9.dist-info/RECORD
