Metadata-Version: 2.1
Name: nengo-sphinx-theme
Version: 20.9
Summary: Sphinx theme for Nengo project documentation pages
Home-page: https://www.nengo.ai/nengo-sphinx-theme
Author: Applied Brain Research
Author-email: info@appliedbrainresearch.com
License: Free for non-commercial use
Platform: UNKNOWN
Classifier: Development Status :: 4 - Beta
Classifier: Framework :: Nengo
Classifier: Intended Audience :: Developers
Classifier: License :: Free for non-commercial use
Classifier: Operating System :: Microsoft :: Windows
Classifier: Operating System :: POSIX :: Linux
Classifier: Programming Language :: Python
Classifier: Programming Language :: Python :: 3.5
Classifier: Programming Language :: Python :: 3.6
Classifier: Programming Language :: Python :: 3.7
Classifier: Topic :: Software Development
Requires-Python: >=3.5
Requires-Dist: sphinx (>=3.0.0)
Requires-Dist: sphinx-notfound-page (>=0.5.0)
Requires-Dist: backoff (>=1.10.0)
Provides-Extra: all
Requires-Dist: jupyter ; extra == 'all'
Requires-Dist: matplotlib ; extra == 'all'
Requires-Dist: nbsphinx ; extra == 'all'
Requires-Dist: nengo ; extra == 'all'
Requires-Dist: numpydoc ; extra == 'all'
Provides-Extra: docs
Requires-Dist: jupyter ; extra == 'docs'
Requires-Dist: matplotlib ; extra == 'docs'
Requires-Dist: nbsphinx ; extra == 'docs'
Requires-Dist: nengo ; extra == 'docs'
Requires-Dist: numpydoc ; extra == 'docs'
Provides-Extra: optional
Provides-Extra: tests
